app/__init__.py
app/api.py
app/cli.py
app/main.py
app/models.py
app/schemas.py
app/core/__init__.py
app/core/actions_router.py
app/core/config.py
app/core/lifespan.py
app/core/lifespan_factory.py
app/core/logging_config.py
app/core/logging_crud.py
app/core/responses.py
app/db/__init__.py
app/db/cache.py
app/db/session.py
app/exceptions/__init__.py
app/exceptions/error_codes.py
app/exceptions/exceptions.py
app/exceptions/handlers.py
app/middleware/__init__.py
app/middleware/logging.py
app/routes/__init__.py
app/routes/items.py
app/routes/user.py
app/routes/useritems.py
my_fastapi_scaffold-0.4.0.dist-info/METADATA
my_fastapi_scaffold-0.4.0.dist-info/WHEEL
my_fastapi_scaffold-0.4.0.dist-info/entry_points.txt
my_fastapi_scaffold-0.4.0.dist-info/top_level.txt
my_fastapi_scaffold-0.4.0.dist-info/RECORD
