Metadata-Version: 2.4
Name: my-fastapi-scaffold
Version: 0.4.0
Summary: 一个功能完备的企业级 FastAPI 脚手架
Author-email: Your Name <your.email@example.com>
License: MIT
Classifier: Programming Language :: Python :: 3
Classifier: Operating System :: OS Independent
Classifier: Framework :: FastAPI
Requires-Python: >=3.9
Requires-Dist: fastapi[all]
Requires-Dist: SQLAlchemy==2.0.41
Requires-Dist: pydantic-settings
Requires-Dist: aiomysql
Requires-Dist: asyncmy
Requires-Dist: redis
Requires-Dist: fastcrud==0.16.0
Requires-Dist: typer[all]
Requires-Dist: python-dotenv
